[
  {
    "vendor": "BitMain",
    "name": "S9",
    "os": "",
    "hashrate": 12800,
    "power": 1400,
    "price": 1400
  },
  {
    "vendor": "BitMain",
    "name": "S7",
    "os": "",
    "hashrate": 4600,
    "power": 1400,
    "price": 1300
  },
  {
    "vendor": "BitMain",
    "name": "S5",
    "os": "",
    "hashrate": 2000,
    "power": 1200,
    "price": 1000
  },
  {
    "vendor": "Avalon",
    "name": "Avalon6",
    "os": "",
    "hashrate": 3650,
    "power": 1160,
    "price": 1520
  },
  {
    "vendor": "Spondoolies",
    "name": "SP35",
    "os": "",
    "hashrate": 5500,
    "power": 3000,
    "price": 2235
  }
]
